Metadata-Version: 2.1
Name: dtool-lookup-server-search-plugin-mongo
Version: 0.2.0
Summary: Search plugin for dtool-lookup-server using mongodb
Home-page: https://github.com/jic-dtool/dtool-lookup-server-search-plugin-mongo
Download-URL: https://github.com/jic-dtool/dtool-lookup-server-search-plugin-mongo/tarball/0.2.0
Author: Tjelvar Olsson
Author-email: tjelvar.olsson@gmail.com
License: MIT
License-File: LICENSE.rst
